django_smalluuid/__init__.py
django_smalluuid/forms.py
django_smalluuid/models.py
django_smalluuid/settings.py
tests/__init__.py
tests/manage.py
tests/settings.py
tests/urls.py
tests/testapp/__init__.py
tests/testapp/forms.py
tests/testapp/models.py
tests/testapp/tests.py
tests/testapp/views.py
django_smalluuid-1.2.0.dist-info/LICENSE.txt
django_smalluuid-1.2.0.dist-info/METADATA
django_smalluuid-1.2.0.dist-info/WHEEL
django_smalluuid-1.2.0.dist-info/top_level.txt
django_smalluuid-1.2.0.dist-info/RECORD
