Metadata-Version: 2.1
Name: django-smalluuid
Version: 1.2.0
Summary: Short-form UUID field for Django 1.8 and above
Home-page: https://github.com/adamcharnock/django-smalluuid
Author: Adam Charnock
Author-email: adam@adamcharnock.com
License: MIT
Platform: UNKNOWN
Requires-Dist: django (>=1.8)
Requires-Dist: smalluuid (>=1.0.1)
Requires-Dist: six
